mATLASplotlib/__init__.py
mATLASplotlib/matplotlib_wrapper.py
mATLASplotlib/canvases/__init__.py
mATLASplotlib/canvases/base_canvas.py
mATLASplotlib/canvases/panelled.py
mATLASplotlib/canvases/ratio.py
mATLASplotlib/canvases/simple.py
mATLASplotlib/converters/__init__.py
mATLASplotlib/converters/dataset.py
mATLASplotlib/converters/root2data.py
mATLASplotlib/decorations/__init__.py
mATLASplotlib/decorations/atlas_text.py
mATLASplotlib/decorations/legend.py
mATLASplotlib/decorations/text.py
mATLASplotlib/formatters/__init__.py
mATLASplotlib/formatters/label.py
mATLASplotlib/plotters/__init__.py
mATLASplotlib/plotters/bar_chart.py
mATLASplotlib/plotters/base_plotter.py
mATLASplotlib/plotters/binned_band.py
mATLASplotlib/plotters/coloured_2D.py
mATLASplotlib/plotters/get_plotter.py
mATLASplotlib/plotters/line.py
mATLASplotlib/plotters/scatter.py
mATLASplotlib/plotters/stack.py
mATLASplotlib/style/__init__.py
mATLASplotlib/style/atlas.py
mATLASplotlib-1.1.0.dist-info/METADATA
mATLASplotlib-1.1.0.dist-info/RECORD
mATLASplotlib-1.1.0.dist-info/WHEEL
mATLASplotlib-1.1.0.dist-info/top_level.txt
tests/__init__.py
tests/canvases/__init__.py
tests/canvases/test_canvases_base.py
tests/canvases/test_canvases_panelled.py
tests/canvases/test_canvases_ratio.py
tests/canvases/test_canvases_simple.py
tests/canvases/test_ratio.py
tests/canvases/test_simple.py
tests/converters/__init__.py
tests/converters/test_converters_dataset.py
tests/converters/test_converters_root2data.py
tests/decorations/__init__.py
tests/decorations/test_decorations_atlas_text.py
tests/decorations/test_decorations_legend.py
tests/decorations/test_decorations_luminosity.py
tests/decorations/test_decorations_text.py
tests/plotters/__init__.py
tests/plotters/test_plotters_bar_chart.py
tests/plotters/test_plotters_base_plotter.py
tests/plotters/test_plotters_binned_band.py
tests/plotters/test_plotters_coloured_2D.py
tests/plotters/test_plotters_get_plotter.py
tests/plotters/test_plotters_line.py
tests/plotters/test_plotters_scatter.py
tests/plotters/test_plotters_stack.py
