Metadata-Version: 2.1
Name: mATLASplotlib
Version: 1.1.0
Summary: Wrappers around matplotlib functionality to produce plots compatible with the style guidelines for the ATLAS experiment at the LHC
Home-page: https://github.com/jemrobinson/mATLASplotlib
Author: James Robinson
Author-email: james.em.robinson@gmail.com
License: GPLv3
Platform: UNKNOWN
Requires-Dist: matplotlib
Requires-Dist: numpy
Requires-Dist: scipy
